flitz_compress/__init__.py
flitz_compress-0.0.2.dist-info/entry_points.txt
flitz_compress-0.0.2.dist-info/WHEEL
flitz_compress-0.0.2.dist-info/METADATA
flitz_compress-0.0.2.dist-info/RECORD
