Metadata-Version: 2.1
Name: flitz-compress
Version: 0.0.2
Summary: Add a context menu element
Author-email: Martin Thoma <info@martin-thoma.de>
Maintainer-email: Martin Thoma <info@martin-thoma.de>
Requires-Python: >=3.10
Classifier: Development Status :: 2 - Pre-Alpha
Classifier: Operating System :: MacOS
Classifier: Operating System :: POSIX :: Linux
Classifier: Programming Language :: Python :: 3 :: Only
Classifier: Programming Language :: Python :: 3.10
Classifier: Programming Language :: Python :: 3.11
Classifier: Programming Language :: Python :: 3.12
Classifier: Typing :: Typed
Requires-Dist: flitz
